rtpt/__init__.py
rtpt/rtpt.py
rtpt/schedule_process.py
rtpt-0.0.4.dist-info/LICENSE
rtpt-0.0.4.dist-info/METADATA
rtpt-0.0.4.dist-info/WHEEL
rtpt-0.0.4.dist-info/top_level.txt
rtpt-0.0.4.dist-info/RECORD
