Metadata-Version: 2.1
Name: rtpt
Version: 0.0.4
Summary: Remaining Time to Process Title
Home-page: https://github.com/ml-research/rtpt
Author: Quentin Delfosse, Patrick Schramowski, Steven Lang, Johannes Czech
Author-email: quentin.delfosse@cs.tu-darmstadt.de
License: UNKNOWN
Platform: UNKNOWN
Classifier: Programming Language :: Python :: 3
Classifier: License :: OSI Approved :: MIT License
Classifier: Operating System :: OS Independent
Requires-Dist: setproctitle
Requires-Dist: gpustat
Requires-Dist: argparse
